newp/__init__.py
newp/cli.py
newp/naming.py
newp/options.py
newp/projects/__init__.py
newp/projects/cpp.py
newp/projects/javascript.py
newp/projects/python.py
newp/templates.py
newp-0.0.6.dist-info/entry_points.txt
newp-0.0.6.dist-info/WHEEL
newp-0.0.6.dist-info/METADATA
newp-0.0.6.dist-info/RECORD
